LICENSE
MANIFEST.in
README.md
pyproject.toml
requirements.txt
setup.cfg
setup.py
clayrs/__init__.py
clayrs.egg-info/PKG-INFO
clayrs.egg-info/SOURCES.txt
clayrs.egg-info/dependency_links.txt
clayrs.egg-info/requires.txt
clayrs.egg-info/top_level.txt
clayrs/content_analyzer/__init__.py
clayrs/content_analyzer/config.py
clayrs/content_analyzer/content_analyzer_main.py
clayrs/content_analyzer/exceptions.py
clayrs/content_analyzer/exogenous_properties_retrieval.py
clayrs/content_analyzer/raw_information_source.py
clayrs/content_analyzer/content_representation/__init__.py
clayrs/content_analyzer/content_representation/content.py
clayrs/content_analyzer/content_representation/representation_container.py
clayrs/content_analyzer/embeddings/__init__.py
clayrs/content_analyzer/embeddings/embedding_source.py
clayrs/content_analyzer/embeddings/embedding_learner/__init__.py
clayrs/content_analyzer/embeddings/embedding_learner/doc2vec.py
clayrs/content_analyzer/embeddings/embedding_learner/embedding_learner.py
clayrs/content_analyzer/embeddings/embedding_learner/fasttext.py
clayrs/content_analyzer/embeddings/embedding_learner/latent_semantic_analysis.py
clayrs/content_analyzer/embeddings/embedding_learner/lda.py
clayrs/content_analyzer/embeddings/embedding_learner/random_indexing.py
clayrs/content_analyzer/embeddings/embedding_learner/word2vec.py
clayrs/content_analyzer/embeddings/embedding_loader/__init__.py
clayrs/content_analyzer/embeddings/embedding_loader/embedding_loader.py
clayrs/content_analyzer/embeddings/embedding_loader/gensim.py
clayrs/content_analyzer/embeddings/embedding_loader/sbert.py
clayrs/content_analyzer/embeddings/embedding_loader/transformer.py
clayrs/content_analyzer/embeddings/embedding_loader/vector_strategy.py
clayrs/content_analyzer/field_content_production_techniques/__init__.py
clayrs/content_analyzer/field_content_production_techniques/field_content_production_technique.py
clayrs/content_analyzer/field_content_production_techniques/synset_document_frequency.py
clayrs/content_analyzer/field_content_production_techniques/tf_idf.py
