Metadata-Version: 2.1
Name: clayrs
Version: 0.5.1
Summary: Complexly represent contents, build recommender systems, evaluate them. All in one place!
Home-page: https://github.com/swapUniba/ClayRS
Author: Antonio Silletti, Elio Musacchio, Roberta Sallustio
License: GPL-3.0
Keywords: recommender system,cbrs,evaluation,recsys
Platform: UNKNOWN
Classifier: Development Status :: 3 - Alpha
Classifier: Intended Audience :: Developers
Classifier: License :: OSI Approved :: GNU General Public License v3 (GPLv3)
Classifier: Operating System :: OS Independent
Classifier: Programming Language :: Python
Classifier: Programming Language :: Python :: 3
Classifier: Programming Language :: Python :: 3 :: Only
Classifier: Programming Language :: Python :: 3.8
Classifier: Programming Language :: Python :: 3.9
Classifier: Programming Language :: Python :: 3.10
Classifier: Topic :: Software Development :: Libraries
Classifier: Topic :: Software Development :: Libraries :: Python Modules
Classifier: Topic :: Software Development :: Testing :: Unit
Requires-Python: >=3.8
License-File: LICENSE
